stitch/__init__.py
stitch/__main__.py
stitchup-0.1.0.dist-info/METADATA
stitchup-0.1.0.dist-info/WHEEL
stitchup-0.1.0.dist-info/top_level.txt
stitchup-0.1.0.dist-info/RECORD
