Metadata-Version: 2.4
Name: stitchup
Version: 0.1.0
Summary: A tool to stitch up together multiple python files into a single file (just like Rollup JS)
Author: Amit Malaker
Dynamic: author
Dynamic: summary
